yaspop/__init__.py
yaspop/common.py
yaspop/configurator.py
yaspop/settings.py
yaspop/yaspop.py
yaspop-0.1.0.dist-info/AUTHORS.rst
yaspop-0.1.0.dist-info/LICENSE
yaspop-0.1.0.dist-info/METADATA
yaspop-0.1.0.dist-info/WHEEL
yaspop-0.1.0.dist-info/top_level.txt
yaspop-0.1.0.dist-info/RECORD
