Metadata-Version: 2.1
Name: yaspop
Version: 0.1.0
Summary: yaspop is yet another simple python option parser. use it and make pop proud.
Home-page: https://github.com/ismaelharunid/yaspop
Author: Ismael Harun
Author-email: ismaelharunid@gmail.com
License: GNU General Public License v3
Keywords: yaspop
Platform: UNKNOWN
Classifier: Development Status :: 2 - Pre-Alpha
Classifier: Intended Audience :: Developers
Classifier: License :: OSI Approved :: GNU General Public License v3 (GPLv3)
Classifier: Natural Language :: English
Classifier: Programming Language :: Python :: 3
Classifier: Programming Language :: Python :: 3.5
Classifier: Programming Language :: Python :: 3.6
Classifier: Programming Language :: Python :: 3.7
Classifier: Programming Language :: Python :: 3.8
Requires-Python: >=3.5
